[
    {
        "name": "Sebastián Hernández",
        "matches": "184",
        "ID_transfermarkt": "73693",
        "name_transfermarkt": "sebastian-hernandez",
        "team": "Independiente Yumbo"
    },
    {
        "name": "Omar Duarte",
        "matches": "169",
        "ID_transfermarkt": "384582",
        "name_transfermarkt": "omar-duarte",
        "team": "Comunicaciones FC"
    },
    {
        "name": "Ronaldo Tavera",
        "matches": "121",
        "ID_transfermarkt": "413554",
        "name_transfermarkt": "ronaldo-tavera",
        "team": "Bogotá FC"
    },
    {
        "name": "Elvis Perlaza",
        "matches": "119",
        "ID_transfermarkt": "74668",
        "name_transfermarkt": "elvis-perlaza",
        "team": "Monagas SC"
    },
    {
        "name": "Jean Becerra",
        "matches": "108",
        "ID_transfermarkt": "253043",
        "name_transfermarkt": "jean-becerra",
        "team": "Without Club"
    },
    {
        "name": "Andrés Amaya",
        "matches": "107",
        "ID_transfermarkt": "572079",
        "name_transfermarkt": "andres-amaya",
        "team": "Fortaleza CEIF"
    },
    {
        "name": "Geovanni Banguera",
        "matches": "106",
        "ID_transfermarkt": "413558",
        "name_transfermarkt": "geovanni-banguera",
        "team": "Asociación Deportivo Pasto"
    },
    {
        "name": "Ervin Maturana",
        "matches": "102",
        "ID_transfermarkt": "77214",
        "name_transfermarkt": "ervin-maturana",
        "team": "Retired"
    },
    {
        "name": "Leonardo Escorcia",
        "matches": "102",
        "ID_transfermarkt": "400087",
        "name_transfermarkt": "leonardo-escorcia",
        "team": "Without Club"
    },
    {
        "name": "Cristian Cangá",
        "matches": "99",
        "ID_transfermarkt": "253045",
        "name_transfermarkt": "cristian-canga",
        "team": "Club Deportivo Rincón"
    },
    {
        "name": "Jeison Méndez",
        "matches": "93",
        "ID_transfermarkt": "950815",
        "name_transfermarkt": "jeison-mendez",
        "team": "Independiente Yumbo"
    },
    {
        "name": "Jefferson Lerma",
        "matches": "92",
        "ID_transfermarkt": "262980",
        "name_transfermarkt": "jefferson-lerma",
        "team": "Crystal Palace"
    },
    {
        "name": "Jorge Ramos",
        "matches": "92",
        "ID_transfermarkt": "117876",
        "name_transfermarkt": "jorge-ramos",
        "team": "Without Club"
    },
    {
        "name": "Nicolás Ayr",
        "matches": "89",
        "ID_transfermarkt": "99398",
        "name_transfermarkt": "nicolas-ayr",
        "team": "Retired"
    },
    {
        "name": "José Ordóñez",
        "matches": "86",
        "ID_transfermarkt": "1231648",
        "name_transfermarkt": "jose-ordonez",
        "team": "Independiente Yumbo"
    },
    {
        "name": "John Méndez",
        "matches": "86",
        "ID_transfermarkt": "955471",
        "name_transfermarkt": "john-mendez",
        "team": "Asociación Deportivo Pasto"
    },
    {
        "name": "Luis Estacio",
        "matches": "85",
        "ID_transfermarkt": "76909",
        "name_transfermarkt": "luis-estacio",
        "team": "Retired"
    },
    {
        "name": "Carlos Díaz",
        "matches": "83",
        "ID_transfermarkt": "73376",
        "name_transfermarkt": "carlos-diaz",
        "team": "Retired"
    },
    {
        "name": "Amílcar Henríquez",
        "matches": "81",
        "ID_transfermarkt": "116328",
        "name_transfermarkt": "amilcar-henriquez",
        "team": "---"
    },
    {
        "name": "Elacio Córdoba",
        "matches": "81",
        "ID_transfermarkt": "242522",
        "name_transfermarkt": "elacio-cordoba",
        "team": "Without Club"
    },
    {
        "name": "Eddie Segura",
        "matches": "80",
        "ID_transfermarkt": "459466",
        "name_transfermarkt": "eddie-segura",
        "team": "Los Angeles FC"
    },
    {
        "name": "Carlos Robles",
        "matches": "80",
        "ID_transfermarkt": "119914",
        "name_transfermarkt": "carlos-robles",
        "team": "Without Club"
    },
    {
        "name": "Julián Rodríguez",
        "matches": "79",
        "ID_transfermarkt": "959221",
        "name_transfermarkt": "julian-rodriguez",
        "team": "Independiente Yumbo"
    },
    {
        "name": "Édinson Palomino",
        "matches": "78",
        "ID_transfermarkt": "117872",
        "name_transfermarkt": "edinson-palomino",
        "team": "Retired"
    },
    {
        "name": "Elvis González",
        "matches": "74",
        "ID_transfermarkt": "73353",
        "name_transfermarkt": "elvis-gonzalez",
        "team": "Retired"
    },
    {
        "name": "Jhon Lerma",
        "matches": "73",
        "ID_transfermarkt": "983539",
        "name_transfermarkt": "jhon-lerma",
        "team": "Independiente Yumbo"
    },
    {
        "name": "Jhon Lozano",
        "matches": "72",
        "ID_transfermarkt": "95910",
        "name_transfermarkt": "jhon-lozano",
        "team": "Retired"
    },
    {
        "name": "Breiner Moya",
        "matches": "72",
        "ID_transfermarkt": "1118338",
        "name_transfermarkt": "breiner-moya",
        "team": "Independiente Yumbo"
    },
    {
        "name": "Yosimarc Torres",
        "matches": "71",
        "ID_transfermarkt": "700206",
        "name_transfermarkt": "yosimarc-torres",
        "team": "Deportes Quindío"
    },
    {
        "name": "Daniel Bocanegra",
        "matches": "67",
        "ID_transfermarkt": "129257",
        "name_transfermarkt": "daniel-bocanegra",
        "team": "Without Club"
    },
    {
        "name": "Gonzalo Martínez",
        "matches": "65",
        "ID_transfermarkt": "5885",
        "name_transfermarkt": "gonzalo-martinez",
        "team": "Retired"
    },
    {
        "name": "Faber Gil",
        "matches": "64",
        "ID_transfermarkt": "422990",
        "name_transfermarkt": "faber-gil",
        "team": "Jaguares de Córdoba"
    },
    {
        "name": "Jhony Da Silva",
        "matches": "62",
        "ID_transfermarkt": "127439",
        "name_transfermarkt": "jhony-da-silva",
        "team": "Miramar Misiones"
    },
    {
        "name": "Camilo Ayala",
        "matches": "62",
        "ID_transfermarkt": "73678",
        "name_transfermarkt": "camilo-ayala",
        "team": "Retired"
    },
    {
        "name": "Jean Carlos Blanco",
        "matches": "60",
        "ID_transfermarkt": "119336",
        "name_transfermarkt": "jean-carlos-blanco",
        "team": "Manta FC"
    },
    {
        "name": "Yonatan Murillo",
        "matches": "59",
        "ID_transfermarkt": "242546",
        "name_transfermarkt": "yonatan-murillo",
        "team": "Sport Huancayo"
    },
    {
        "name": "Hernán Hechalar",
        "matches": "59",
        "ID_transfermarkt": "76151",
        "name_transfermarkt": "hernan-hechalar",
        "team": "CSDM San Miguel (Salta)"
    },
    {
        "name": "Óscar Rueda",
        "matches": "59",
        "ID_transfermarkt": "74109",
        "name_transfermarkt": "oscar-rueda",
        "team": "Retired"
    },
    {
        "name": "Jorge Vidal",
        "matches": "59",
        "ID_transfermarkt": "74508",
        "name_transfermarkt": "jorge-vidal",
        "team": "Retired"
    },
    {
        "name": "Harlin Suárez",
        "matches": "58",
        "ID_transfermarkt": "485730",
        "name_transfermarkt": "harlin-suarez",
        "team": "Internacional de Palmira"
    },
    {
        "name": "Francisco Rodríguez",
        "matches": "58",
        "ID_transfermarkt": "119253",
        "name_transfermarkt": "francisco-rodriguez",
        "team": "Independiente Yumbo"
    },
    {
        "name": "Carlos Sánchez",
        "matches": "57",
        "ID_transfermarkt": "914209",
        "name_transfermarkt": "carlos-sanchez",
        "team": "Cumbayá FC"
    },
    {
        "name": "Blas Díaz",
        "matches": "57",
        "ID_transfermarkt": "248441",
        "name_transfermarkt": "blas-diaz",
        "team": "Encarnacena FC"
    },
    {
        "name": "Ayron del Valle",
        "matches": "57",
        "ID_transfermarkt": "74440",
        "name_transfermarkt": "ayron-del-valle",
        "team": "Alianza FC"
    },
    {
        "name": "Iván Garrido",
        "matches": "56",
        "ID_transfermarkt": "74415",
        "name_transfermarkt": "ivan-garrido",
        "team": "Retired"
    },
    {
        "name": "César Hinestroza",
        "matches": "56",
        "ID_transfermarkt": "156555",
        "name_transfermarkt": "cesar-hinestroza",
        "team": "Without Club"
    },
    {
        "name": "Dayron Pérez",
        "matches": "56",
        "ID_transfermarkt": "75502",
        "name_transfermarkt": "dayron-perez",
        "team": "Retired"
    },
    {
        "name": "Harold Rivera",
        "matches": "56",
        "ID_transfermarkt": "211391",
        "name_transfermarkt": "harold-rivera",
        "team": "Junior FC"
    },
    {
        "name": "Michael Ordóñez",
        "matches": "54",
        "ID_transfermarkt": "308253",
        "name_transfermarkt": "michael-ordonez",
        "team": "Retired"
    },
    {
        "name": "Lucas Farías",
        "matches": "53",
        "ID_transfermarkt": "754679",
        "name_transfermarkt": "lucas-farias",
        "team": "Independiente Yumbo"
    },
    {
        "name": "Jader Manyoma",
        "matches": "53",
        "ID_transfermarkt": "1146411",
        "name_transfermarkt": "jader-manyoma",
        "team": "Independiente Yumbo"
    },
    {
        "name": "Maicol Sequeda",
        "matches": "53",
        "ID_transfermarkt": "1111694",
        "name_transfermarkt": "maicol-sequeda",
        "team": "Independiente Yumbo"
    },
    {
        "name": "Bréiner Belalcázar",
        "matches": "52",
        "ID_transfermarkt": "73679",
        "name_transfermarkt": "breiner-belalcazar",
        "team": "Retired"
    },
    {
        "name": "Didier Moreno",
        "matches": "52",
        "ID_transfermarkt": "182122",
        "name_transfermarkt": "didier-moreno",
        "team": "Independiente Medellín"
    },
    {
        "name": "Andrés Rivera",
        "matches": "49",
        "ID_transfermarkt": "242557",
        "name_transfermarkt": "andres-rivera",
        "team": "Without Club"
    },
    {
        "name": "Tomás Díaz",
        "matches": "49",
        "ID_transfermarkt": "1179937",
        "name_transfermarkt": "tomas-diaz",
        "team": "Independiente Yumbo"
    },
    {
        "name": "Jhon Figueroa",
        "matches": "48",
        "ID_transfermarkt": "639167",
        "name_transfermarkt": "jhon-figueroa",
        "team": "Leones FC"
    },
    {
        "name": "Jean Carlos Pestaña",
        "matches": "48",
        "ID_transfermarkt": "572076",
        "name_transfermarkt": "jean-carlos-pestana",
        "team": "Junior FC"
    },
    {
        "name": "Brayan Moreno",
        "matches": "48",
        "ID_transfermarkt": "778476",
        "name_transfermarkt": "brayan-moreno",
        "team": "Without Club"
    },
    {
        "name": "Iván Velásquez",
        "matches": "47",
        "ID_transfermarkt": "77318",
        "name_transfermarkt": "ivan-velasquez",
        "team": "Retired"
    },
    {
        "name": "Carlos Abella",
        "matches": "46",
        "ID_transfermarkt": "76905",
        "name_transfermarkt": "carlos-abella",
        "team": "Retired"
    },
    {
        "name": "Manuel Berrío",
        "matches": "46",
        "ID_transfermarkt": "413559",
        "name_transfermarkt": "manuel-berrio",
        "team": "Unknown"
    },
    {
        "name": "Marco Canchila",
        "matches": "46",
        "ID_transfermarkt": "75482",
        "name_transfermarkt": "marco-canchila",
        "team": "Retired"
    },
    {
        "name": "Carlos Carbonero",
        "matches": "45",
        "ID_transfermarkt": "136605",
        "name_transfermarkt": "carlos-carbonero",
        "team": "Without Club"
    },
    {
        "name": "Jhony Cano",
        "matches": "45",
        "ID_transfermarkt": "133523",
        "name_transfermarkt": "jhony-cano",
        "team": "Without Club"
    },
    {
        "name": "Dylan Lozano",
        "matches": "45",
        "ID_transfermarkt": "950839",
        "name_transfermarkt": "dylan-lozano",
        "team": "Rionegro Águilas"
    },
    {
        "name": "Anderson Rojas",
        "matches": "44",
        "ID_transfermarkt": "1231647",
        "name_transfermarkt": "anderson-rojas",
        "team": "Independiente Yumbo"
    },
    {
        "name": "Williams Buenaños",
        "matches": "43",
        "ID_transfermarkt": "145826",
        "name_transfermarkt": "williams-buenanos",
        "team": "Unknown"
    },
    {
        "name": "Luis Hinestroza",
        "matches": "43",
        "ID_transfermarkt": "1149272",
        "name_transfermarkt": "luis-hinestroza",
        "team": "Without Club"
    },
    {
        "name": "Ernesto Hernández",
        "matches": "42",
        "ID_transfermarkt": "74255",
        "name_transfermarkt": "ernesto-hernandez",
        "team": "CA Fénix"
    },
    {
        "name": "Andrés Correa",
        "matches": "42",
        "ID_transfermarkt": "177973",
        "name_transfermarkt": "andres-correa",
        "team": "Retired"
    },
    {
        "name": "Andrés Ricaurte",
        "matches": "42",
        "ID_transfermarkt": "253846",
        "name_transfermarkt": "andres-ricaurte",
        "team": "Rionegro Águilas"
    },
    {
        "name": "Gustavo Britos",
        "matches": "42",
        "ID_transfermarkt": "419314",
        "name_transfermarkt": "gustavo-britos",
        "team": "Leones de Rosario FC"
    },
    {
        "name": "Nelson Barahona",
        "matches": "42",
        "ID_transfermarkt": "76668",
        "name_transfermarkt": "nelson-barahona",
        "team": "Retired"
    },
    {
        "name": "Freyn Figueroa",
        "matches": "42",
        "ID_transfermarkt": "572075",
        "name_transfermarkt": "freyn-figueroa",
        "team": "Boyacá Patriotas FC"
    },
    {
        "name": "Mateo Fígoli",
        "matches": "41",
        "ID_transfermarkt": "55332",
        "name_transfermarkt": "mateo-figoli",
        "team": "CA Ituzaingó (Maldonado)"
    },
    {
        "name": "Víctor Guazá",
        "matches": "40",
        "ID_transfermarkt": "72631",
        "name_transfermarkt": "victor-guaza",
        "team": "Retired"
    },
    {
        "name": "Marvin Vallecilla",
        "matches": "39",
        "ID_transfermarkt": "356457",
        "name_transfermarkt": "marvin-vallecilla",
        "team": "Without Club"
    },
    {
        "name": "Danny Ferrer",
        "matches": "39",
        "ID_transfermarkt": "1350516",
        "name_transfermarkt": "danny-ferrer",
        "team": "Independiente Yumbo"
    },
    {
        "name": "Marcus Vinicius",
        "matches": "39",
        "ID_transfermarkt": "934680",
        "name_transfermarkt": "marcus-vinicius",
        "team": "Without Club"
    },
    {
        "name": "Víctor Moreno",
        "matches": "38",
        "ID_transfermarkt": "626675",
        "name_transfermarkt": "victor-moreno",
        "team": "Independiente Santa Fe"
    },
    {
        "name": "Edisson Restrepo",
        "matches": "38",
        "ID_transfermarkt": "345653",
        "name_transfermarkt": "edisson-restrepo",
        "team": "Club Always Ready"
    },
    {
        "name": "Bréiner Castillo",
        "matches": "38",
        "ID_transfermarkt": "28146",
        "name_transfermarkt": "breiner-castillo",
        "team": "Retired"
    },
    {
        "name": "David Ferreira",
        "matches": "38",
        "ID_transfermarkt": "53340",
        "name_transfermarkt": "david-ferreira",
        "team": "Retired"
    },
    {
        "name": "Diego Arias",
        "matches": "38",
        "ID_transfermarkt": "77277",
        "name_transfermarkt": "diego-arias",
        "team": "Retired"
    },
    {
        "name": "Rafael Castillo",
        "matches": "38",
        "ID_transfermarkt": "74409",
        "name_transfermarkt": "rafael-castillo",
        "team": "Retired"
    },
    {
        "name": "Cristian Restrepo",
        "matches": "38",
        "ID_transfermarkt": "88853",
        "name_transfermarkt": "cristian-restrepo",
        "team": "Unknown"
    },
    {
        "name": "Michael López",
        "matches": "38",
        "ID_transfermarkt": "600859",
        "name_transfermarkt": "michael-lopez",
        "team": "Retired"
    },
    {
        "name": "Carlos Moreno",
        "matches": "37",
        "ID_transfermarkt": "346714",
        "name_transfermarkt": "carlos-moreno",
        "team": "Without Club"
    },
    {
        "name": "César Valoyes",
        "matches": "37",
        "ID_transfermarkt": "74112",
        "name_transfermarkt": "cesar-valoyes",
        "team": "Retired"
    },
    {
        "name": "Santiago Muñoz",
        "matches": "37",
        "ID_transfermarkt": "632614",
        "name_transfermarkt": "santiago-munoz",
        "team": "Al-Ahly SC"
    },
    {
        "name": "Carlos Ramírez",
        "matches": "36",
        "ID_transfermarkt": "77306",
        "name_transfermarkt": "carlos-ramirez",
        "team": "Internacional de Palmira"
    },
    {
        "name": "César Mena",
        "matches": "36",
        "ID_transfermarkt": "147097",
        "name_transfermarkt": "cesar-mena",
        "team": "Without Club"
    },
    {
        "name": "Edwar López",
        "matches": "36",
        "ID_transfermarkt": "572077",
        "name_transfermarkt": "edwar-lopez",
        "team": "Deportes Tolima"
    },
    {
        "name": "Kevin Agudelo",
        "matches": "36",
        "ID_transfermarkt": "587458",
        "name_transfermarkt": "kevin-agudelo",
        "team": "Al-Nasr SC (UAE)"
    },
    {
        "name": "Yuber Asprilla",
        "matches": "36",
        "ID_transfermarkt": "130516",
        "name_transfermarkt": "yuber-asprilla",
        "team": "Without Club"
    },
    {
        "name": "Luis Fernández",
        "matches": "35",
        "ID_transfermarkt": "91053",
        "name_transfermarkt": "luis-fernandez",
        "team": "Retired"
    },
    {
        "name": "Andrés Ariza",
        "matches": "35",
        "ID_transfermarkt": "663163",
        "name_transfermarkt": "andres-ariza",
        "team": "Club Deportivo Oriente Petrolero"
    },
    {
        "name": "Juan Niño",
        "matches": "35",
        "ID_transfermarkt": "265484",
        "name_transfermarkt": "juan-nino",
        "team": "Unknown"
    },
    {
        "name": "Marcelo Bergese",
        "matches": "35",
        "ID_transfermarkt": "87506",
        "name_transfermarkt": "marcelo-bergese",
        "team": "Retired"
    }
]