[
    {
        "club": "Atlético Nacional",
        "matches": 762,
        "wins": 366,
        "goal_diff": 397,
        "points": 1308
    },
    {
        "club": "Deportes Tolima",
        "matches": 761,
        "wins": 338,
        "goal_diff": 257,
        "points": 1230
    },
    {
        "club": "Millonarios FC",
        "matches": 740,
        "wins": 328,
        "goal_diff": 254,
        "points": 1186
    },
    {
        "club": "Junior de Barranquilla",
        "matches": 752,
        "wins": 312,
        "goal_diff": 208,
        "points": 1163
    },
    {
        "club": "Independiente Santa Fe",
        "matches": 736,
        "wins": 309,
        "goal_diff": 188,
        "points": 1150
    },
    {
        "club": "Independiente Medellín",
        "matches": 721,
        "wins": 302,
        "goal_diff": 175,
        "points": 1117
    },
    {
        "club": "Deportivo Cali",
        "matches": 699,
        "wins": 257,
        "goal_diff": 47,
        "points": 979
    },
    {
        "club": "Once Caldas",
        "matches": 683,
        "wins": 244,
        "goal_diff": 41,
        "points": 934
    },
    {
        "club": "Internacional de Bogotá",
        "matches": 673,
        "wins": 209,
        "goal_diff": -47,
        "points": 867
    },
    {
        "club": "Águilas Doradas",
        "matches": 625,
        "wins": 218,
        "goal_diff": 2,
        "points": 852
    },
    {
        "club": "Asociación Deportivo Pasto",
        "matches": 603,
        "wins": 193,
        "goal_diff": -60,
        "points": 766
    },
    {
        "club": "CD América de Cali",
        "matches": 506,
        "wins": 194,
        "goal_diff": 76,
        "points": 726
    },
    {
        "club": "Envigado FC",
        "matches": 629,
        "wins": 172,
        "goal_diff": -146,
        "points": 715
    },
    {
        "club": "Alianza FC",
        "matches": 514,
        "wins": 154,
        "goal_diff": -135,
        "points": 609
    },
    {
        "club": "Atlético Bucaramanga",
        "matches": 414,
        "wins": 150,
        "goal_diff": -2,
        "points": 569
    },
    {
        "club": "Independiente Yumbo",
        "matches": 488,
        "wins": 140,
        "goal_diff": -126,
        "points": 562
    },
    {
        "club": "Boyacá Chicó FC",
        "matches": 496,
        "wins": 127,
        "goal_diff": -200,
        "points": 530
    },
    {
        "club": "Boyacá Patriotas FC",
        "matches": 449,
        "wins": 126,
        "goal_diff": -131,
        "points": 517
    },
    {
        "club": "Jaguares de Córdoba",
        "matches": 386,
        "wins": 99,
        "goal_diff": -165,
        "points": 412
    },
    {
        "club": "Deportivo Pereira",
        "matches": 343,
        "wins": 99,
        "goal_diff": -49,
        "points": 408
    },
    {
        "club": "Cúcuta Deportivo",
        "matches": 283,
        "wins": 72,
        "goal_diff": -110,
        "points": 298
    },
    {
        "club": "Deportes Quindío",
        "matches": 188,
        "wins": 56,
        "goal_diff": -91,
        "points": 211
    },
    {
        "club": "Internacional de Palmira",
        "matches": 200,
        "wins": 49,
        "goal_diff": -82,
        "points": 198
    },
    {
        "club": "Fortaleza CEIF",
        "matches": 167,
        "wins": 47,
        "goal_diff": -45,
        "points": 192
    },
    {
        "club": "Unión Magdalena",
        "matches": 166,
        "wins": 36,
        "goal_diff": -102,
        "points": 158
    },
    {
        "club": "CD Real Cartagena",
        "matches": 132,
        "wins": 37,
        "goal_diff": -53,
        "points": 148
    },
    {
        "club": "Uniautónoma FC (2010 - 2015)",
        "matches": 76,
        "wins": 17,
        "goal_diff": -43,
        "points": 72
    },
    {
        "club": "Llaneros FC",
        "matches": 47,
        "wins": 15,
        "goal_diff": -15,
        "points": 54
    },
    {
        "club": "Tigres FC",
        "matches": 40,
        "wins": 11,
        "goal_diff": -18,
        "points": 45
    },
    {
        "club": "Leones FC",
        "matches": 38,
        "wins": 3,
        "goal_diff": -23,
        "points": 22
    },
    {
        "club": "Club Boca Juniors de Cali",
        "matches": 1,
        "wins": 0,
        "goal_diff": -2,
        "points": 0
    }
]