{
    "player_id": "101259",
    "profile": {
        "short_name": "A. Kasem",
        "nation_1": "Egypt",
        "nation_2": "",
        "height": null,
        "foot": null,
        "position_group": "DEFENDER",
        "position_1": "SW",
        "position_2": "",
        "position_3": "",
        "former_clubs": "",
        "market_value": null,
        "prime_date": null
    },
    "clubs": {
        "664": {
            "importance": {
                "presence": 0.929872,
                "sporting": 0.42759498078770414,
                "titles": 0.8951058369858154,
                "individual": 0.0,
                "total": 0.6541346106728595
            },
            "positions": {
                "SW": null
            }
        },
        "3672": {
            "importance": {
                "presence": 0.3385173333333333,
                "sporting": 0.2901869918699187,
                "titles": 0.7220396944482013,
                "individual": 0.0,
                "total": 0.3644544527107784
            },
            "positions": {
                "SW": null
            }
        },
        "1114": {
            "importance": {
                "presence": 0.04066666666666668,
                "sporting": 0.0,
                "titles": 0.0,
                "individual": 0.0,
                "total": 0.014233333333333336
            },
            "positions": {
                "SW": null
            }
        }
    }
}