{
    "player_id": "149403",
    "profile": {
        "short_name": "C. Magnier",
        "nation_1": "France",
        "nation_2": "",
        "height": 1.82,
        "foot": "",
        "position_group": "DEFENDER",
        "position_1": "CB",
        "position_2": "",
        "position_3": "",
        "former_clubs": "",
        "market_value": null,
        "prime_date": null
    },
    "clubs": {
        "16051": {
            "importance": {
                "presence": 0.04066666666666668,
                "sporting": 0.0,
                "titles": 0.0,
                "individual": 0.0,
                "total": 0.014233333333333336
            },
            "positions": {
                "CB": null
            }
        },
        "1416": {
            "importance": {
                "presence": 0.1966026666666667,
                "sporting": 0.2881254901960784,
                "titles": 0.0,
                "individual": 0.0,
                "total": 0.16965485490196078
            },
            "positions": {
                "CB": null
            }
        },
        "290": {
            "importance": {
                "presence": 0.23773866666666665,
                "sporting": 0.11699449035812672,
                "titles": 0.0,
                "individual": 0.0,
                "total": 0.12415660495867767
            },
            "positions": {
                "CB": null
            }
        },
        "826": {
            "importance": {
                "presence": 1.0,
                "sporting": 0.3341984435797666,
                "titles": 0.6324714110546878,
                "individual": 0.0,
                "total": 0.5934637374638558
            },
            "positions": {
                "CB": 40
            }
        },
        "9323": {
            "importance": {
                "presence": 0.08685333333333334,
                "sporting": 0.24266666666666667,
                "titles": 0.0,
                "individual": 0.0,
                "total": 0.115332
            },
            "positions": {
                "CB": null
            }
        }
    }
}