{
    "player_id": "237779",
    "profile": {
        "short_name": "A. Maslyonkin",
        "nation_1": "Russia",
        "nation_2": null,
        "height": 1.78,
        "foot": "Right",
        "position_group": "DEFENDER",
        "position_1": "SW",
        "position_2": "DMF",
        "position_3": "CB",
        "former_clubs": "",
        "market_value": null,
        "prime_date": null
    },
    "clubs": {
        "2374": {
            "importance": {
                "presence": 0.19821333333333332,
                "sporting": 0.4934146341463414,
                "titles": 0.0,
                "individual": 0.0,
                "total": 0.24206978861788614
            },
            "positions": {
                "SW": null,
                "DMF": null,
                "CB": null
            }
        },
        "232": {
            "importance": {
                "presence": 0.9084266666666667,
                "sporting": 0.44203496503496503,
                "titles": 0.7779617734035771,
                "individual": 0.0,
                "total": 0.6282539257762865
            },
            "positions": {
                "SW": null,
                "DMF": null,
                "CB": null
            }
        },
        "17203": {
            "importance": {
                "presence": 0.44425066666666674,
                "sporting": 0.3076494252873563,
                "titles": 0.7325342506107698,
                "individual": 0.0,
                "total": 0.40967188230606205
            },
            "positions": {
                "CB": 17
            }
        },
        "53889": {
            "importance": {
                "presence": 0.04621333333333334,
                "sporting": 0.22399999999999998,
                "titles": 0.6966394958706764,
                "individual": 0.0,
                "total": 0.23390256584080193
            },
            "positions": {
                "DMF": 2
            }
        },
        "69534": {
            "importance": {
                "presence": 0.041386666666666676,
                "sporting": 0.105,
                "titles": 0.0,
                "individual": 0.0,
                "total": 0.051235333333333334
            },
            "positions": {
                "SW": null,
                "DMF": null,
                "CB": null
            }
        }
    }
}