{
    "player_id": "251123",
    "profile": {
        "short_name": "J. Sissons",
        "nation_1": "England",
        "nation_2": "",
        "height": null,
        "foot": "Left",
        "position_group": "FORWARD",
        "position_1": "LW",
        "position_2": "",
        "position_3": "",
        "former_clubs": "",
        "market_value": null,
        "prime_date": null
    },
    "clubs": {
        "1123": {
            "importance": {
                "presence": 0.18514666666666668,
                "sporting": 0.2003155737704918,
                "titles": 0.0,
                "individual": 0.0,
                "total": 0.13491178415300548
            },
            "positions": {
                "LW": null
            }
        },
        "631": {
            "importance": {
                "presence": 0.07747733333333334,
                "sporting": 0.19388541666666664,
                "titles": 0.0,
                "individual": 0.0,
                "total": 0.09497696249999998
            },
            "positions": {
                "LW": 8
            }
        },
        "1035": {
            "importance": {
                "presence": 0.3149866666666667,
                "sporting": 0.010120481927710841,
                "titles": 0.0,
                "individual": 0.0,
                "total": 0.11378750200803213
            },
            "positions": {
                "LW": null
            }
        },
        "379": {
            "importance": {
                "presence": 0.889424,
                "sporting": 0.4814175347222222,
                "titles": 0.7914255537228804,
                "individual": 0.0,
                "total": 0.6380796478973538
            },
            "positions": {
                "LW": 86
            }
        }
    }
}