{
    "player_id": "298682",
    "profile": {
        "short_name": "M. Al-Shatnawi",
        "nation_1": "Jordan",
        "nation_2": "",
        "height": 1.91,
        "foot": "Right",
        "position_group": "GOALKEEPER",
        "position_1": "GK",
        "position_2": "",
        "position_3": "",
        "former_clubs": "",
        "market_value": null,
        "prime_date": null
    },
    "clubs": {
        "15737": {
            "importance": {
                "presence": 0.37485333333333337,
                "sporting": 0.06892307692307692,
                "titles": 0.0,
                "individual": 0.0,
                "total": 0.1553217435897436
            },
            "positions": {
                "GK": null
            }
        },
        "13592": {
            "importance": {
                "presence": 0.14752,
                "sporting": 0.18666666666666665,
                "titles": 0.0,
                "individual": 0.0,
                "total": 0.11696533333333334
            },
            "positions": {
                "GK": null
            }
        },
        "15795": {
            "importance": {
                "presence": 0.04400000000000001,
                "sporting": 0.0,
                "titles": 0.0,
                "individual": 0.0,
                "total": 0.015400000000000002
            },
            "positions": {
                "GK": null
            }
        }
    }
}