{
    "player_id": "352890",
    "profile": {
        "short_name": "Mateus Gonçalves",
        "nation_1": "Brazil",
        "nation_2": "",
        "height": 1.72,
        "foot": "Right",
        "position_group": "FORWARD",
        "position_1": "LW",
        "position_2": "RW",
        "position_3": "AMF",
        "former_clubs": "",
        "market_value": 1000000,
        "prime_date": "2019-02-18"
    },
    "clubs": {
        "64918": {
            "importance": {
                "presence": 0.06562133333333335,
                "sporting": 0.25738141025641026,
                "titles": 0.0,
                "individual": 0.0,
                "total": 0.11305096025641026
            },
            "positions": {
                "LW": null,
                "RW": null,
                "AMF": null
            }
        },
        "3197": {
            "importance": {
                "presence": 0.06522133333333335,
                "sporting": 0.24842628205128203,
                "titles": 0.0,
                "individual": 0.0,
                "total": 0.10977666538461538
            },
            "positions": {
                "LW": null,
                "RW": null,
                "AMF": null
            }
        },
        "2125": {
            "importance": {
                "presence": 0.1536906666666667,
                "sporting": 0.3019427083333333,
                "titles": 0.38572417711649964,
                "individual": 0.0,
                "total": 0.23661651667329991
            },
            "positions": {
                "LW": null,
                "RW": null,
                "AMF": null
            }
        },
        "2863": {
            "importance": {
                "presence": 0.06768000000000002,
                "sporting": 0.16277525252525252,
                "titles": 0.0,
                "individual": 0.0,
                "total": 0.08065933838383837
            },
            "positions": {
                "LW": null,
                "RW": null,
                "AMF": null
            }
        },
        "1214": {
            "importance": {
                "presence": 0.16760000000000003,
                "sporting": 0.13628819444444445,
                "titles": 0.0,
                "individual": 0.0,
                "total": 0.10636086805555556
            },
            "positions": {
                "LW": null,
                "RW": null,
                "AMF": null
            }
        },
        "2029": {
            "importance": {
                "presence": 0.181296,
                "sporting": 0.235687908496732,
                "titles": 0.0,
                "individual": 0.0,
                "total": 0.14594436797385618
            },
            "positions": {
                "LW": null,
                "RW": null,
                "AMF": null
            }
        },
        "2462": {
            "importance": {
                "presence": 0.05604800000000001,
                "sporting": 0.030888888888888886,
                "titles": 0.0,
                "individual": 0.0,
                "total": 0.03042791111111111
            },
            "positions": {
                "LW": null,
                "RW": null,
                "AMF": null
            }
        },
        "8718": {
            "importance": {
                "presence": 0.06875733333333334,
                "sporting": 0.46234166666666665,
                "titles": 0.0,
                "individual": 0.0,
                "total": 0.18588464999999998
            },
            "positions": {
                "LW": 11
            }
        },
        "13353": {
            "importance": {
                "presence": 0.10677866666666669,
                "sporting": 0.3503293010752688,
                "titles": 0.0,
                "individual": 0.0,
                "total": 0.1599877887096774
            },
            "positions": {
                "LW": null,
                "RW": null,
                "AMF": null
            }
        },
        "32585": {
            "importance": {
                "presence": 0.05076266666666668,
                "sporting": 0.2967333333333333,
                "titles": 0.0,
                "individual": 0.0,
                "total": 0.12162359999999998
            },
            "positions": {
                "LW": null,
                "RW": null,
                "AMF": null
            }
        },
        "1804": {
            "importance": {
                "presence": 0.06188800000000001,
                "sporting": 0.17140277777777774,
                "titles": 0.0,
                "individual": 0.0,
                "total": 0.08165177222222221
            },
            "positions": {
                "LW": 12
            }
        },
        "25781": {
            "importance": {
                "presence": 0.047546666666666675,
                "sporting": 0.15999999999999998,
                "titles": 0.0,
                "individual": 0.0,
                "total": 0.07264133333333332
            },
            "positions": {
                "LW": null,
                "RW": null,
                "AMF": null
            }
        },
        "4774": {
            "importance": {
                "presence": 0.06594666666666668,
                "sporting": 0.1702272727272727,
                "titles": 0.0,
                "individual": 0.0,
                "total": 0.08266087878787878
            },
            "positions": {
                "LW": 5
            }
        },
        "26079": {
            "importance": {
                "presence": 0.041386666666666676,
                "sporting": 0.105,
                "titles": 0.0,
                "individual": 0.0,
                "total": 0.051235333333333334
            },
            "positions": {
                "LW": null,
                "RW": null,
                "AMF": null
            }
        },
        "4035": {
            "importance": {
                "presence": 0.10046400000000001,
                "sporting": 0.37087499999999995,
                "titles": 0.7127388685717257,
                "individual": 0.0,
                "total": 0.3075164237143452
            },
            "positions": {
                "LW": null,
                "RW": null,
                "AMF": null
            }
        },
        "25929": {
            "importance": {
                "presence": 0.046640000000000015,
                "sporting": 0.1808333333333333,
                "titles": 0.0,
                "individual": 0.0,
                "total": 0.07961566666666665
            },
            "positions": {
                "LW": null,
                "RW": null,
                "AMF": null
            }
        },
        "34545": {
            "importance": {
                "presence": 0.11130666666666669,
                "sporting": 0.6295484496124031,
                "titles": 0.0,
                "individual": 0.0,
                "total": 0.2592992906976744
            },
            "positions": {
                "LW": 10,
                "RW": 10
            }
        },
        "20831": {
            "importance": {
                "presence": 0.05114666666666668,
                "sporting": 0.05474358974358974,
                "titles": 0.0,
                "individual": 0.0,
                "total": 0.03706158974358975
            },
            "positions": {
                "LW": null,
                "RW": null,
                "AMF": null
            }
        },
        "15136": {
            "importance": {
                "presence": 0.04200000000000001,
                "sporting": 0.0,
                "titles": 0.0,
                "individual": 0.0,
                "total": 0.014700000000000003
            },
            "positions": {
                "LW": null,
                "RW": null,
                "AMF": null
            }
        }
    }
}