{
    "player_id": "37732",
    "profile": {
        "short_name": "S. Nkosi",
        "nation_1": "South Africa",
        "nation_2": "",
        "height": null,
        "foot": null,
        "position_group": "MIDFIELDER",
        "position_1": "AMF",
        "position_2": "CMF",
        "position_3": "SS",
        "former_clubs": "Riverview Spurs, Greenpoint Vultures, Orlando Pirates (2001-2003)",
        "market_value": 700000,
        "prime_date": "2007-07-17"
    },
    "clubs": {
        "568": {
            "importance": {
                "presence": 0.3259146666666667,
                "sporting": 0.32888175675675674,
                "titles": 0.6966394958706764,
                "individual": 0.0,
                "total": 0.36850664737233346
            },
            "positions": {
                "CMF": 15,
                "AMF": 12
            }
        },
        "7011": {
            "importance": {
                "presence": 0.1834346666666667,
                "sporting": 0.5908749999999999,
                "titles": 0.0,
                "individual": 0.0,
                "total": 0.2710083833333333
            },
            "positions": {
                "AMF": 16
            }
        },
        "2891": {
            "importance": {
                "presence": 0.08449066666666669,
                "sporting": 0.3386114864864864,
                "titles": 0.5240957019060464,
                "individual": 0.0,
                "total": 0.25290489398481286
            },
            "positions": {
                "AMF": null,
                "CMF": null,
                "SS": null
            }
        },
        "3806": {
            "importance": {
                "presence": 0.297696,
                "sporting": 0.17996944444444443,
                "titles": 0.0,
                "individual": 0.0,
                "total": 0.16718290555555554
            },
            "positions": {
                "AMF": null,
                "CMF": null,
                "SS": null
            }
        },
        "5223": {
            "importance": {
                "presence": 0.07237866666666667,
                "sporting": 0.3853522727272727,
                "titles": 0.0,
                "individual": 0.0,
                "total": 0.16020582878787876
            },
            "positions": {
                "AMF": null,
                "CMF": null,
                "SS": null
            }
        },
        "10": {
            "importance": {
                "presence": 0.12558933333333333,
                "sporting": 0.06524999999999999,
                "titles": 0.0,
                "individual": 0.0,
                "total": 0.06679376666666666
            },
            "positions": {
                "AMF": null,
                "CMF": null,
                "SS": null
            }
        },
        "8607": {
            "importance": {
                "presence": 0.12000000000000002,
                "sporting": 0.0,
                "titles": 0.0,
                "individual": 0.0,
                "total": 0.042
            },
            "positions": {
                "AMF": null,
                "CMF": null,
                "SS": null
            }
        }
    }
}