{
    "player_id": "555892",
    "profile": {
        "short_name": "Shunzo Ono",
        "nation_1": "Japan",
        "nation_2": "",
        "height": 1.77,
        "foot": "",
        "position_group": "DEFENDER",
        "position_1": "CB",
        "position_2": "",
        "position_3": "",
        "former_clubs": "",
        "market_value": null,
        "prime_date": null
    },
    "clubs": {
        "593": {
            "importance": {
                "presence": 0.084512,
                "sporting": 0.13258518518518517,
                "titles": 0.0,
                "individual": 0.0,
                "total": 0.07598401481481482
            },
            "positions": {
                "CB": null
            }
        },
        "2241": {
            "importance": {
                "presence": 0.7144106666666666,
                "sporting": 0.21329054054054053,
                "titles": 0.0,
                "individual": 0.0,
                "total": 0.3246954225225225
            },
            "positions": {
                "CB": 46
            }
        },
        "3435": {
            "importance": {
                "presence": 0.04333333333333334,
                "sporting": 0.0,
                "titles": 0.0,
                "individual": 0.0,
                "total": 0.015166666666666669
            },
            "positions": {
                "CB": null
            }
        }
    }
}