{
    "player_id": "624521",
    "profile": {
        "short_name": "Don Megson",
        "nation_1": "England",
        "nation_2": "",
        "height": null,
        "foot": null,
        "position_group": "DEFENDER",
        "position_1": "LB",
        "position_2": "LM",
        "position_3": "",
        "former_clubs": "",
        "market_value": null,
        "prime_date": null
    },
    "clubs": {
        "2455": {
            "importance": {
                "presence": 0.05088000000000001,
                "sporting": 0.09333333333333332,
                "titles": 0.0,
                "individual": 0.0,
                "total": 0.05047466666666667
            },
            "positions": {
                "LB": null,
                "LM": null
            }
        },
        "1035": {
            "importance": {
                "presence": 1.0,
                "sporting": 0.4707224462365591,
                "titles": 0.0,
                "individual": 0.0,
                "total": 0.5147528561827956
            },
            "positions": {
                "LB": 37
            }
        }
    }
}